{
  "as_of": "2026-06-22",
  "n_holdings": 100,
  "active_share_l1": 0.2382,
  "active_share_one_way": 0.1191,
  "concentration": {
    "top5_weight": 0.338339,
    "top10_weight": 0.522926,
    "effective_names": 27.41,
    "max_name_weight": 0.093371,
    "max_name_active_abs": 0.038322,
    "top5_active_budget_share": 0.485455,
    "top10_active_budget_share": 0.6448
  },
  "top_ow": [
    {
      "ticker": "285A",
      "weight": 0.04513,
      "bm_weight": 0.00681,
      "active": 0.03832,
      "sector": "Technology"
    },
    {
      "ticker": "SNDK",
      "weight": 0.04411,
      "bm_weight": 0.00623,
      "active": 0.03788,
      "sector": "Technology"
    },
    {
      "ticker": "NOVOB",
      "weight": 0.02296,
      "bm_weight": 0.00379,
      "active": 0.01918,
      "sector": "Healthcare"
    },
    {
      "ticker": "ARM",
      "weight": 0.01806,
      "bm_weight": 0.00805,
      "active": 0.01,
      "sector": "Technology"
    },
    {
      "ticker": "PLTR",
      "weight": 0.00861,
      "bm_weight": 0.0053,
      "active": 0.00331,
      "sector": "Technology"
    },
    {
      "ticker": "DLR",
      "weight": 0.00458,
      "bm_weight": 0.00129,
      "active": 0.00328,
      "sector": "Real Estate"
    },
    {
      "ticker": "MU",
      "weight": 0.02845,
      "bm_weight": 0.02526,
      "active": 0.00319,
      "sector": "Technology"
    },
    {
      "ticker": "MRVL",
      "weight": 0.00813,
      "bm_weight": 0.00498,
      "active": 0.00315,
      "sector": "Technology"
    },
    {
      "ticker": "LITE",
      "weight": 0.00188,
      "bm_weight": 0.00129,
      "active": 0.00059,
      "sector": "Technology"
    },
    {
      "ticker": "FN",
      "weight": 0.00058,
      "bm_weight": 0.00041,
      "active": 0.00017,
      "sector": "Technology"
    },
    {
      "ticker": "MSFT",
      "weight": 0.05046,
      "bm_weight": 0.05046,
      "active": -0.0,
      "sector": "Technology"
    },
    {
      "ticker": "NVDA",
      "weight": 0.09337,
      "bm_weight": 0.09337,
      "active": -0.0,
      "sector": "Technology"
    }
  ],
  "top_uw": [
    {
      "ticker": "TSLA",
      "weight": 0.0179,
      "bm_weight": 0.02813,
      "active": -0.01024,
      "sector": "Consumer Discretionary"
    },
    {
      "ticker": "INTC",
      "weight": 0.00528,
      "bm_weight": 0.0131,
      "active": -0.00782,
      "sector": "Technology"
    },
    {
      "ticker": "GOOGL",
      "weight": 0.07086,
      "bm_weight": 0.07863,
      "active": -0.00777,
      "sector": "Technology"
    },
    {
      "ticker": "LRCX",
      "weight": 0.00184,
      "bm_weight": 0.00947,
      "active": -0.00763,
      "sector": "Technology"
    },
    {
      "ticker": "META",
      "weight": 0.01907,
      "bm_weight": 0.02647,
      "active": -0.00739,
      "sector": "Technology"
    },
    {
      "ticker": "AMZN",
      "weight": 0.03897,
      "bm_weight": 0.04631,
      "active": -0.00733,
      "sector": "Consumer Discretionary"
    },
    {
      "ticker": "ASML",
      "weight": 0.00837,
      "bm_weight": 0.01358,
      "active": -0.00522,
      "sector": "Technology"
    },
    {
      "ticker": "ORCL",
      "weight": 0.00482,
      "bm_weight": 0.00933,
      "active": -0.00451,
      "sector": "Technology"
    },
    {
      "ticker": "000660",
      "weight": 0.02105,
      "bm_weight": 0.02537,
      "active": -0.00432,
      "sector": "Technology"
    },
    {
      "ticker": "005930",
      "weight": 0.02094,
      "bm_weight": 0.02507,
      "active": -0.00413,
      "sector": "Technology"
    },
    {
      "ticker": "TSM",
      "weight": 0.04083,
      "bm_weight": 0.04485,
      "active": -0.00402,
      "sector": "Technology"
    },
    {
      "ticker": "AMAT",
      "weight": 0.00551,
      "bm_weight": 0.0094,
      "active": -0.00389,
      "sector": "Technology"
    }
  ],
  "all": [
    {
      "ticker": "285A",
      "weight": 0.04513,
      "bm_weight": 0.00681,
      "active": 0.03832,
      "sector": "Technology"
    },
    {
      "ticker": "SNDK",
      "weight": 0.04411,
      "bm_weight": 0.00623,
      "active": 0.03788,
      "sector": "Technology"
    },
    {
      "ticker": "NOVOB",
      "weight": 0.02296,
      "bm_weight": 0.00379,
      "active": 0.01918,
      "sector": "Healthcare"
    },
    {
      "ticker": "ARM",
      "weight": 0.01806,
      "bm_weight": 0.00805,
      "active": 0.01,
      "sector": "Technology"
    },
    {
      "ticker": "PLTR",
      "weight": 0.00861,
      "bm_weight": 0.0053,
      "active": 0.00331,
      "sector": "Technology"
    },
    {
      "ticker": "DLR",
      "weight": 0.00458,
      "bm_weight": 0.00129,
      "active": 0.00328,
      "sector": "Real Estate"
    },
    {
      "ticker": "MU",
      "weight": 0.02845,
      "bm_weight": 0.02526,
      "active": 0.00319,
      "sector": "Technology"
    },
    {
      "ticker": "MRVL",
      "weight": 0.00813,
      "bm_weight": 0.00498,
      "active": 0.00315,
      "sector": "Technology"
    },
    {
      "ticker": "LITE",
      "weight": 0.00188,
      "bm_weight": 0.00129,
      "active": 0.00059,
      "sector": "Technology"
    },
    {
      "ticker": "FN",
      "weight": 0.00058,
      "bm_weight": 0.00041,
      "active": 0.00017,
      "sector": "Technology"
    },
    {
      "ticker": "MSFT",
      "weight": 0.05046,
      "bm_weight": 0.05046,
      "active": -0.0,
      "sector": "Technology"
    },
    {
      "ticker": "NVDA",
      "weight": 0.09337,
      "bm_weight": 0.09337,
      "active": -0.0,
      "sector": "Technology"
    },
    {
      "ticker": "REGN",
      "weight": 0.00119,
      "bm_weight": 0.00119,
      "active": -0.0,
      "sector": "Healthcare"
    },
    {
      "ticker": "BLK",
      "weight": 0.00318,
      "bm_weight": 0.00318,
      "active": -0.0,
      "sector": "Financials"
    },
    {
      "ticker": "SPGI",
      "weight": 0.00228,
      "bm_weight": 0.00228,
      "active": -0.0,
      "sector": "Financials"
    },
    {
      "ticker": "MCD",
      "weight": 0.00355,
      "bm_weight": 0.00355,
      "active": -0.0,
      "sector": "Consumer Discretionary"
    },
    {
      "ticker": "UNP",
      "weight": 0.00285,
      "bm_weight": 0.00285,
      "active": -0.0,
      "sector": "Industrials"
    },
    {
      "ticker": "LNG",
      "weight": 0.00089,
      "bm_weight": 0.00089,
      "active": -0.0,
      "sector": "Energy"
    },
    {
      "ticker": "NEE",
      "weight": 0.00332,
      "bm_weight": 0.00332,
      "active": -0.0,
      "sector": "Utilities"
    },
    {
      "ticker": "AMT",
      "weight": 0.00152,
      "bm_weight": 0.00152,
      "active": -0.0,
      "sector": "Real Estate"
    },
    {
      "ticker": "TMUS",
      "weight": 0.0036,
      "bm_weight": 0.0036,
      "active": -0.0,
      "sector": "Communication Services"
    },
    {
      "ticker": "PLD",
      "weight": 0.00254,
      "bm_weight": 0.00254,
      "active": -0.0,
      "sector": "Real Estate"
    },
    {
      "ticker": "CRM",
      "weight": 0.00227,
      "bm_weight": 0.00227,
      "active": -0.0,
      "sector": "Technology"
    },
    {
      "ticker": "NFLX",
      "weight": 0.00567,
      "bm_weight": 0.00567,
      "active": -0.0,
      "sector": "Communication Services"
    },
    {
      "ticker": "MPC",
      "weight": 0.00133,
      "bm_weight": 0.00133,
      "active": -0.0,
      "sector": "Energy"
    },
    {
      "ticker": "BX",
      "weight": 0.00281,
      "bm_weight": 0.00281,
      "active": -0.0,
      "sector": "Financials"
    },
    {
      "ticker": "BKNG",
      "weight": 0.0024,
      "bm_weight": 0.0024,
      "active": -0.0,
      "sector": "Consumer Discretionary"
    },
    {
      "ticker": "PM",
      "weight": 0.00499,
      "bm_weight": 0.00499,
      "active": -0.0,
      "sector": "Consumer Staples"
    },
    {
      "ticker": "WMB",
      "weight": 0.00169,
      "bm_weight": 0.00169,
      "active": -0.0,
      "sector": "Energy"
    },
    {
      "ticker": "SPOT",
      "weight": 0.00175,
      "bm_weight": 0.00175,
      "active": -0.0,
      "sector": "Communication Services"
    },
    {
      "ticker": "RACE",
      "weight": 0.00114,
      "bm_weight": 0.00114,
      "active": -0.0,
      "sector": "Consumer Discretionary"
    },
    {
      "ticker": "RHM",
      "weight": 0.00116,
      "bm_weight": 0.00116,
      "active": -0.0,
      "sector": "Industrials"
    },
    {
      "ticker": "ALV",
      "weight": 0.00326,
      "bm_weight": 0.00326,
      "active": -0.0,
      "sector": "Financials"
    },
    {
      "ticker": "MC",
      "weight": 0.00504,
      "bm_weight": 0.00504,
      "active": -0.0,
      "sector": "Consumer Discretionary"
    },
    {
      "ticker": "NESN",
      "weight": 0.00465,
      "bm_weight": 0.00465,
      "active": -0.0,
      "sector": "Consumer Staples"
    },
    {
      "ticker": "SAP",
      "weight": 0.0034,
      "bm_weight": 0.0034,
      "active": -0.0,
      "sector": "Technology"
    },
    {
      "ticker": "WFC",
      "weight": 0.00472,
      "bm_weight": 0.00474,
      "active": -2e-05,
      "sector": "Financials"
    },
    {
      "ticker": "SHEL",
      "weight": 0.00409,
      "bm_weight": 0.00411,
      "active": -2e-05,
      "sector": "Energy"
    },
    {
      "ticker": "TMO",
      "weight": 0.00312,
      "bm_weight": 0.00319,
      "active": -7e-05,
      "sector": "Healthcare"
    },
    {
      "ticker": "XOM",
      "weight": 0.01052,
      "bm_weight": 0.01061,
      "active": -9e-05,
      "sector": "Energy"
    },
    {
      "ticker": "PG",
      "weight": 0.00617,
      "bm_weight": 0.00636,
      "active": -0.00018,
      "sector": "Consumer Staples"
    },
    {
      "ticker": "CEG",
      "weight": 0.00165,
      "bm_weight": 0.00185,
      "active": -0.00019,
      "sector": "Utilities"
    },
    {
      "ticker": "MA",
      "weight": 0.00768,
      "bm_weight": 0.00791,
      "active": -0.00023,
      "sector": "Financials"
    },
    {
      "ticker": "ISRG",
      "weight": 0.00237,
      "bm_weight": 0.00264,
      "active": -0.00027,
      "sector": "Healthcare"
    },
    {
      "ticker": "BAC",
      "weight": 0.00726,
      "bm_weight": 0.00753,
      "active": -0.00027,
      "sector": "Financials"
    },
    {
      "ticker": "HSBA",
      "weight": 0.00585,
      "bm_weight": 0.00611,
      "active": -0.00027,
      "sector": "Financials"
    },
    {
      "ticker": "CSCO",
      "weight": 0.00856,
      "bm_weight": 0.00886,
      "active": -0.00029,
      "sector": "Technology"
    },
    {
      "ticker": "CDNS",
      "weight": 0.00169,
      "bm_weight": 0.00198,
      "active": -0.00029,
      "sector": "Technology"
    },
    {
      "ticker": "DE",
      "weight": 0.00268,
      "bm_weight": 0.00299,
      "active": -0.00031,
      "sector": "Industrials"
    },
    {
      "ticker": "V",
      "weight": 0.01131,
      "bm_weight": 0.01166,
      "active": -0.00035,
      "sector": "Financials"
    },
    {
      "ticker": "LMT",
      "weight": 0.00173,
      "bm_weight": 0.0021,
      "active": -0.00038,
      "sector": "Industrials"
    },
    {
      "ticker": "LIN",
      "weight": 0.00401,
      "bm_weight": 0.00442,
      "active": -0.00041,
      "sector": "Materials"
    },
    {
      "ticker": "HD",
      "weight": 0.00559,
      "bm_weight": 0.00602,
      "active": -0.00043,
      "sector": "Consumer Discretionary"
    },
    {
      "ticker": "VST",
      "weight": 0.00059,
      "bm_weight": 0.00104,
      "active": -0.00045,
      "sector": "Utilities"
    },
    {
      "ticker": "COST",
      "weight": 0.00734,
      "bm_weight": 0.0078,
      "active": -0.00046,
      "sector": "Consumer Staples"
    },
    {
      "ticker": "HON",
      "weight": 0.0022,
      "bm_weight": 0.00267,
      "active": -0.00047,
      "sector": "Industrials"
    },
    {
      "ticker": "RIO",
      "weight": 0.00269,
      "bm_weight": 0.00316,
      "active": -0.00047,
      "sector": "Materials"
    },
    {
      "ticker": "EQIX",
      "weight": 0.00155,
      "bm_weight": 0.00204,
      "active": -0.00049,
      "sector": "Real Estate"
    },
    {
      "ticker": "GS",
      "weight": 0.00574,
      "bm_weight": 0.00627,
      "active": -0.00053,
      "sector": "Financials"
    },
    {
      "ticker": "ETN",
      "weight": 0.00258,
      "bm_weight": 0.00313,
      "active": -0.00055,
      "sector": "Industrials"
    },
    {
      "ticker": "ABBV",
      "weight": 0.00691,
      "bm_weight": 0.00751,
      "active": -0.00061,
      "sector": "Healthcare"
    },
    {
      "ticker": "FCX",
      "weight": 0.00118,
      "bm_weight": 0.00184,
      "active": -0.00066,
      "sector": "Materials"
    },
    {
      "ticker": "PWR",
      "weight": 0.00138,
      "bm_weight": 0.00205,
      "active": -0.00068,
      "sector": "Industrials"
    },
    {
      "ticker": "JNJ",
      "weight": 0.00961,
      "bm_weight": 0.0103,
      "active": -0.00069,
      "sector": "Healthcare"
    },
    {
      "ticker": "RR/",
      "weight": 0.0022,
      "bm_weight": 0.00289,
      "active": -0.00069,
      "sector": "Industrials"
    },
    {
      "ticker": "VRT",
      "weight": 0.00181,
      "bm_weight": 0.00254,
      "active": -0.00073,
      "sector": "Industrials"
    },
    {
      "ticker": "KLAC",
      "weight": 0.00575,
      "bm_weight": 0.0065,
      "active": -0.00076,
      "sector": "Technology"
    },
    {
      "ticker": "UNH",
      "weight": 0.00605,
      "bm_weight": 0.00683,
      "active": -0.00078,
      "sector": "Healthcare"
    },
    {
      "ticker": "GLW",
      "weight": 0.00255,
      "bm_weight": 0.00333,
      "active": -0.00078,
      "sector": "Technology"
    },
    {
      "ticker": "MPWR",
      "weight": 0.00061,
      "bm_weight": 0.0014,
      "active": -0.00079,
      "sector": "Technology"
    },
    {
      "ticker": "SU",
      "weight": 0.00273,
      "bm_weight": 0.00357,
      "active": -0.00084,
      "sector": "Industrials"
    },
    {
      "ticker": "SIE",
      "weight": 0.00367,
      "bm_weight": 0.00458,
      "active": -0.00091,
      "sector": "Industrials"
    },
    {
      "ticker": "CAT",
      "weight": 0.00779,
      "bm_weight": 0.00871,
      "active": -0.00092,
      "sector": "Industrials"
    },
    {
      "ticker": "JPM",
      "weight": 0.01535,
      "bm_weight": 0.01642,
      "active": -0.00107,
      "sector": "Financials"
    },
    {
      "ticker": "GEV",
      "weight": 0.00452,
      "bm_weight": 0.0056,
      "active": -0.00108,
      "sector": "Industrials"
    },
    {
      "ticker": "BSX",
      "weight": 6e-05,
      "bm_weight": 0.00122,
      "active": -0.00116,
      "sector": "Healthcare"
    },
    {
      "ticker": "TER",
      "weight": 3e-05,
      "bm_weight": 0.00132,
      "active": -0.0013,
      "sector": "Technology"
    },
    {
      "ticker": "ANET",
      "weight": 0.00264,
      "bm_weight": 0.00406,
      "active": -0.00142,
      "sector": "Technology"
    },
    {
      "ticker": "WMT",
      "weight": 0.01581,
      "bm_weight": 0.01724,
      "active": -0.00143,
      "sector": "Consumer Staples"
    },
    {
      "ticker": "BE",
      "weight": 4e-05,
      "bm_weight": 0.00182,
      "active": -0.00178,
      "sector": "Industrials"
    },
    {
      "ticker": "LLY",
      "weight": 0.01734,
      "bm_weight": 0.01919,
      "active": -0.00185,
      "sector": "Healthcare"
    },
    {
      "ticker": "6857",
      "weight": 0.00079,
      "bm_weight": 0.0027,
      "active": -0.00191,
      "sector": "Technology"
    },
    {
      "ticker": "PANW",
      "weight": 0.00233,
      "bm_weight": 0.00432,
      "active": -0.00199,
      "sector": "Technology"
    },
    {
      "ticker": "AZN",
      "weight": 0.00295,
      "bm_weight": 0.00505,
      "active": -0.0021,
      "sector": "Healthcare"
    },
    {
      "ticker": "AAPL",
      "weight": 0.07852,
      "bm_weight": 0.08067,
      "active": -0.00215,
      "sector": "Technology"
    },
    {
      "ticker": "AVGO",
      "weight": 0.03222,
      "bm_weight": 0.0345,
      "active": -0.00227,
      "sector": "Technology"
    },
    {
      "ticker": "AMD",
      "weight": 0.01384,
      "bm_weight": 0.01663,
      "active": -0.00279,
      "sector": "Technology"
    },
    {
      "ticker": "STX",
      "weight": 0.00133,
      "bm_weight": 0.00454,
      "active": -0.0032,
      "sector": "Technology"
    },
    {
      "ticker": "AMAT",
      "weight": 0.00551,
      "bm_weight": 0.0094,
      "active": -0.00389,
      "sector": "Technology"
    },
    {
      "ticker": "TSM",
      "weight": 0.04083,
      "bm_weight": 0.04485,
      "active": -0.00402,
      "sector": "Technology"
    },
    {
      "ticker": "005930",
      "weight": 0.02094,
      "bm_weight": 0.02507,
      "active": -0.00413,
      "sector": "Technology"
    },
    {
      "ticker": "000660",
      "weight": 0.02105,
      "bm_weight": 0.02537,
      "active": -0.00432,
      "sector": "Technology"
    },
    {
      "ticker": "ORCL",
      "weight": 0.00482,
      "bm_weight": 0.00933,
      "active": -0.00451,
      "sector": "Technology"
    },
    {
      "ticker": "ASML",
      "weight": 0.00837,
      "bm_weight": 0.01358,
      "active": -0.00522,
      "sector": "Technology"
    },
    {
      "ticker": "AMZN",
      "weight": 0.03897,
      "bm_weight": 0.04631,
      "active": -0.00733,
      "sector": "Consumer Discretionary"
    },
    {
      "ticker": "META",
      "weight": 0.01907,
      "bm_weight": 0.02647,
      "active": -0.00739,
      "sector": "Technology"
    },
    {
      "ticker": "LRCX",
      "weight": 0.00184,
      "bm_weight": 0.00947,
      "active": -0.00763,
      "sector": "Technology"
    },
    {
      "ticker": "GOOGL",
      "weight": 0.07086,
      "bm_weight": 0.07863,
      "active": -0.00777,
      "sector": "Technology"
    },
    {
      "ticker": "INTC",
      "weight": 0.00528,
      "bm_weight": 0.0131,
      "active": -0.00782,
      "sector": "Technology"
    },
    {
      "ticker": "TSLA",
      "weight": 0.0179,
      "bm_weight": 0.02813,
      "active": -0.01024,
      "sector": "Consumer Discretionary"
    }
  ]
}